MANIFEST.in
README.md
pycd.sh
requirements.txt
setup.py
completion/_pycd
completion/_pypack
completion/pycd-completion.bash
completion/pypack-completion.bash
pycd/__init__.py
pycd/cli.py
pycd/package.py
pycd.egg-info/PKG-INFO
pycd.egg-info/SOURCES.txt
pycd.egg-info/dependency_links.txt
pycd.egg-info/entry_points.txt
pycd.egg-info/requires.txt
pycd.egg-info/top_level.txt
pycd/tests/__init__.py
pycd/tests/test_package.py