Metadata-Version: 2.1
Name: pycd
Version: 0.3.30
Summary: Tool to change directory for python modules.
Home-page: http://github.com/wkentaro/pycd
Author: Kentaro Wada
Author-email: www.kentaro.wada@gmail.com
License: MIT
Keywords: utility
Platform: UNKNOWN
Classifier: Development Status :: 5 - Production/Stable
Classifier: Intended Audience :: Developers
Classifier: License :: OSI Approved :: MIT License
Classifier: Operating System :: POSIX
Classifier: Topic :: Internet :: WWW/HTTP
